dashmed/Initialize.py
dashmed/__init__.py
dashmed/main.py
dashmed/dash/__init__ .py
dashmed/dash/bpgraph.py
dashmed/dash/display.py
dashmed/database/__init__ .py
dashmed/database/role.py
dashmed/database/sqlite.py
DashMed-0.0.4.dist-info/LICENSE.txt
DashMed-0.0.4.dist-info/METADATA
DashMed-0.0.4.dist-info/WHEEL
DashMed-0.0.4.dist-info/top_level.txt
DashMed-0.0.4.dist-info/RECORD
