Metadata-Version: 2.1
Name: DashMed
Version: 0.0.4
Summary: A Python package that imports patient data from .csv files into a SQLite database, creates a dashboard displaying patient data with a graph of blood pressure over time, and manages user roles with varying permissions for data access and modification.
Author-email: Matthew Angoh <mattangoh@gmail.com>, Shayla Tran <shaylaannatran@gmail.com>
Project-URL: Homepage, https://github.com/mattangoh/DashMed
Project-URL: Issues, https://github.com/mattangoh/DashMed/issues
Classifier: Programming Language :: Python :: 3
Classifier: License :: OSI Approved :: MIT License
Classifier: Operating System :: OS Independent
Requires-Python: >=3.8
License-File: LICENSE.txt
